fcolors/__init__.py
fcolors/fcolors.py
fcolors-0.0.3.dist-info/METADATA
fcolors-0.0.3.dist-info/WHEEL
fcolors-0.0.3.dist-info/licenses/LICENSE
fcolors-0.0.3.dist-info/RECORD
