Metadata-Version: 2.1
Name: fcolors
Version: 0.0.3
Summary: A simple fstring-friendly string colorizer
Project-URL: Homepage, https://gitlab.com/jbunnell/colors
Project-URL: Issues, https://gitlab.com/jbunnell/colors/issues
Author-email: Jayson Bunnell <jaysonbunnell@gmail.com>
License-File: LICENSE
Classifier: Operating System :: OS Independent
Classifier: Programming Language :: Python :: 3
Requires-Python: >=3.8
